{
	"format_version": "1.8.0",
	"animations": {
		"animation.enchantress.idle": {
			"loop": true,
			"animation_length": 6,
			"bones": {
				"leftArm": {
					"rotation": {
						"0.0": [0, 0, 2.5],
						"0.0833": [0, 0, 2.5],
						"2.9167": [0, 0, 0],
						"3.0833": [0, 0, 0],
						"5.9167": [0, 0, 2.5],
						"6.0": [0, 0, 2.5]
					}
				},
				"rightArm": {
					"rotation": {
						"0.0": [0, 0, 2.5],
						"0.0833": [0, 0, 2.5],
						"2.9167": [0, 0, 0],
						"3.0833": [0, 0, 0],
						"5.9167": [0, 0, 2.5],
						"6.0": [0, 0, 2.5]
					}
				},
				"orb": {
					"position": {
						"0.0": [0, 0, 0],
						"0.0833": [0, 0, 0],
						"2.9167": [0, 0.5, 0],
						"3.0833": [0, 0.5, 0],
						"5.9167": [0, 0, 0],
						"6.0": [0, 0, 0]
					}
				}
			}
		}
	}
}